bam_shot/__init__.py
bam_shot/bam.py
bam_shot/img.py
bam_shot-0.0.1.dist-info/LICENSE
bam_shot-0.0.1.dist-info/METADATA
bam_shot-0.0.1.dist-info/WHEEL
bam_shot-0.0.1.dist-info/top_level.txt
bam_shot-0.0.1.dist-info/RECORD
