Metadata-Version: 2.1
Name: bam-shot
Version: 0.0.1
Summary: A tools of bam to image
Home-page: UNKNOWN
Author: Ying Zhu
Author-email: win19890412@163.com
License: UNKNOWN
Platform: UNKNOWN
Classifier: Programming Language :: Python :: 3
Classifier: License :: OSI Approved :: MIT License
Classifier: Operating System :: OS Independent
License-File: LICENSE
Requires-Dist: pysam
